[
  {
    "__type__": "cc.Prefab",
    "_name": "slider",
    "_objFlags": 0,
    "_native": "",
    "data": {
      "__id__": 1
    },
    "optimizationPolicy": 1,
    "asyncLoadAssets": false,
    "readonly": false
  },
  {
    "__type__": "cc.Node",
    "_name": "slider",
    "_objFlags": 0,
    "_parent": null,
    "_children": [
      {
        "__id__": 2
      },
      {
        "__id__": 5
      }
    ],
    "_active": true,
    "_components": [
      {
        "__id__": 9
      }
    ],
    "_prefab": {
      "__id__": 10
    },
    "_opacity": 255,
    "_color": {
      "__type__": "cc.Color",
      "r": 255,
      "g": 255,
      "b": 255,
      "a": 255
    },
    "_contentSize": {
      "__type__": "cc.Size",
      "width": 300,
      "height": 20
    },
    "_anchorPoint": {
      "__type__": "cc.Vec2",
      "x": 0.5,
      "y": 0.5
    },
    "_trs": {
      "__type__": "TypedArray",
      "ctor": "Float64Array",
      "array": [
        0,
        0,
        0,
        0,
        0,
        0,
        1,
        1,
        1,
        1
      ]
    },
    "_eulerAngles": {
      "__type__": "cc.Vec3",
      "x": 0,
      "y": 0,
      "z": 0
    },
    "_skewX": 0,
    "_skewY": 0,
    "_is3DNode": false,
    "_groupIndex": 0,
    "groupIndex": 0,
    "_id": ""
  },
  {
    "__type__": "cc.Node",
    "_name": "Background",
    "_objFlags": 512,
    "_parent": {
      "__id__": 1
    },
    "_children": [],
    "_active": true,
    "_components": [
      {
        "__id__": 3
      }
    ],
    "_prefab": {
      "__id__": 4
    },
    "_opacity": 255,
    "_color": {
      "__type__": "cc.Color",
      "r": 255,
      "g": 255,
      "b": 255,
      "a": 255
    },
    "_contentSize": {
      "__type__": "cc.Size",
      "width": 300,
      "height": 20
    },
    "_anchorPoint": {
      "__type__": "cc.Vec2",
      "x": 0.5,
      "y": 0.5
    },
    "_trs": {
      "__type__": "TypedArray",
      "ctor": "Float64Array",
      "array": [
        0,
        0,
        0,
        0,
        0,
        0,
        1,
        1,
        1,
        1
      ]
    },
    "_eulerAngles": {
      "__type__": "cc.Vec3",
      "x": 0,
      "y": 0,
      "z": 0
    },
    "_skewX": 0,
    "_skewY": 0,
    "_is3DNode": false,
    "_groupIndex": 0,
    "groupIndex": 0,
    "_id": ""
  },
  {
    "__type__": "cc.Sprite",
    "_name": "",
    "_objFlags": 0,
    "node": {
      "__id__": 2
    },
    "_enabled": true,
    "_materials": [
      {
        "__uuid__": "eca5d2f2-8ef6-41c2-bbe6-f9c79d09c432"
      }
    ],
    "_srcBlendFactor": 770,
    "_dstBlendFactor": 771,
    "_spriteFrame": {
      "__uuid__": "31d8962d-babb-4ec7-be19-8e9f54a4ea99"
    },
    "_type": 1,
    "_sizeMode": 0,
    "_fillType": 0,
    "_fillCenter": {
      "__type__": "cc.Vec2",
      "x": 0,
      "y": 0
    },
    "_fillStart": 0,
    "_fillRange": 0,
    "_isTrimmedMode": true,
    "_atlas": null,
    "_id": ""
  },
  {
    "__type__": "cc.PrefabInfo",
    "root": {
      "__id__": 1
    },
    "asset": {
      "__uuid__": "0004d1cf-a0ad-47d8-ab17-34d3db9d35a3"
    },
    "fileId": "f43c4gNvOtBE41OTztiOT6T",
    "sync": false
  },
  {
    "__type__": "cc.Node",
    "_name": "Handle",
    "_objFlags": 512,
    "_parent": {
      "__id__": 1
    },
    "_children": [],
    "_active": true,
    "_components": [
      {
        "__id__": 6
      },
      {
        "__id__": 7
      }
    ],
    "_prefab": {
      "__id__": 8
    },
    "_opacity": 255,
    "_color": {
      "__type__": "cc.Color",
      "r": 255,
      "g": 255,
      "b": 255,
      "a": 255
    },
    "_contentSize": {
      "__type__": "cc.Size",
      "width": 32,
      "height": 32
    },
    "_anchorPoint": {
      "__type__": "cc.Vec2",
      "x": 0.5,
      "y": 0.5
    },
    "_trs": {
      "__type__": "TypedArray",
      "ctor": "Float64Array",
      "array": [
        0,
        0,
        0,
        0,
        0,
        0,
        1,
        1,
        1,
        1
      ]
    },
    "_eulerAngles": {
      "__type__": "cc.Vec3",
      "x": 0,
      "y": 0,
      "z": 0
    },
    "_skewX": 0,
    "_skewY": 0,
    "_is3DNode": false,
    "_groupIndex": 0,
    "groupIndex": 0,
    "_id": ""
  },
  {
    "__type__": "cc.Sprite",
    "_name": "",
    "_objFlags": 0,
    "node": {
      "__id__": 5
    },
    "_enabled": true,
    "_materials": [
      {
        "__uuid__": "eca5d2f2-8ef6-41c2-bbe6-f9c79d09c432"
      }
    ],
    "_srcBlendFactor": 770,
    "_dstBlendFactor": 771,
    "_spriteFrame": {
      "__uuid__": "e7aba14b-f956-4480-b254-8d57832e273f"
    },
    "_type": 1,
    "_sizeMode": 2,
    "_fillType": 0,
    "_fillCenter": {
      "__type__": "cc.Vec2",
      "x": 0,
      "y": 0
    },
    "_fillStart": 0,
    "_fillRange": 0,
    "_isTrimmedMode": true,
    "_atlas": null,
    "_id": ""
  },
  {
    "__type__": "cc.Button",
    "_name": "",
    "_objFlags": 0,
    "node": {
      "__id__": 5
    },
    "_enabled": true,
    "_normalMaterial": null,
    "_grayMaterial": null,
    "duration": 0.1,
    "zoomScale": 1.1,
    "clickEvents": [],
    "_N$interactable": true,
    "_N$enableAutoGrayEffect": true,
    "_N$transition": 3,
    "transition": 3,
    "_N$normalColor": {
      "__type__": "cc.Color",
      "r": 255,
      "g": 255,
      "b": 255,
      "a": 255
    },
    "_N$pressedColor": {
      "__type__": "cc.Color",
      "r": 255,
      "g": 255,
      "b": 255,
      "a": 255
    },
    "pressedColor": {
      "__type__": "cc.Color",
      "r": 255,
      "g": 255,
      "b": 255,
      "a": 255
    },
    "_N$hoverColor": {
      "__type__": "cc.Color",
      "r": 255,
      "g": 255,
      "b": 255,
      "a": 255
    },
    "hoverColor": {
      "__type__": "cc.Color",
      "r": 255,
      "g": 255,
      "b": 255,
      "a": 255
    },
    "_N$disabledColor": {
      "__type__": "cc.Color",
      "r": 255,
      "g": 255,
      "b": 255,
      "a": 255
    },
    "_N$normalSprite": {
      "__uuid__": "e7aba14b-f956-4480-b254-8d57832e273f"
    },
    "_N$pressedSprite": {
      "__uuid__": "e7aba14b-f956-4480-b254-8d57832e273f"
    },
    "pressedSprite": {
      "__uuid__": "e7aba14b-f956-4480-b254-8d57832e273f"
    },
    "_N$hoverSprite": {
      "__uuid__": "e7aba14b-f956-4480-b254-8d57832e273f"
    },
    "hoverSprite": {
      "__uuid__": "e7aba14b-f956-4480-b254-8d57832e273f"
    },
    "_N$disabledSprite": {
      "__uuid__": "29158224-f8dd-4661-a796-1ffab537140e"
    },
    "_N$target": {
      "__id__": 5
    },
    "_id": ""
  },
  {
    "__type__": "cc.PrefabInfo",
    "root": {
      "__id__": 1
    },
    "asset": {
      "__uuid__": "0004d1cf-a0ad-47d8-ab17-34d3db9d35a3"
    },
    "fileId": "93f4b6UTvtD0Iy5hi3tLIn2",
    "sync": false
  },
  {
    "__type__": "cc.Slider",
    "_name": "",
    "_objFlags": 0,
    "node": {
      "__id__": 1
    },
    "_enabled": true,
    "direction": 0,
    "slideEvents": [],
    "_N$handle": {
      "__id__": 7
    },
    "_N$progress": 0.5,
    "_id": ""
  },
  {
    "__type__": "cc.PrefabInfo",
    "root": {
      "__id__": 1
    },
    "asset": {
      "__uuid__": "0004d1cf-a0ad-47d8-ab17-34d3db9d35a3"
    },
    "fileId": "8ac42iRpDlK6pemd22ZO6x/",
    "sync": false
  }
]